setup.cfg
setup.py
simpleplugins/__init__.py
simpleplugins.egg-info/PKG-INFO
simpleplugins.egg-info/SOURCES.txt
simpleplugins.egg-info/dependency_links.txt
simpleplugins.egg-info/top_level.txt