Metadata-Version: 1.1
Name: simpleplugins
Version: 0.1.0
Summary: Extremely simple python plugin framework!
Home-page: https://github.com/TechnicalBro/simple-python-plugins
Author: Brandon Curtis
Author-email: freebird.brandon@gmail.com
License: LICENSE.txt
Platform: UNKNOWN
Classifier: Development Status :: 5 - Production/Stable
Classifier: Intended Audience :: Developers
Classifier: Natural Language :: English
Classifier: License :: OSI Approved :: MIT License
Classifier: Programming Language :: Python
Classifier: Programming Language :: Python :: 3
Classifier: Programming Language :: Python :: 3.3
Classifier: Programming Language :: Python :: 3.4
